openstackclient/__init__.py
openstackclient/command.py
openstackclient/i18n.py
openstackclient/shell.py
openstackclient/api/__init__.py
openstackclient/api/api.py
openstackclient/api/compute_v2.py
openstackclient/api/image_v1.py
openstackclient/api/image_v2.py
openstackclient/api/object_store_v1.py
openstackclient/api/volume_v2.py
openstackclient/api/volume_v3.py
openstackclient/common/__init__.py
openstackclient/common/availability_zone.py
openstackclient/common/clientmanager.py
openstackclient/common/configuration.py
openstackclient/common/envvars.py
openstackclient/common/extension.py
openstackclient/common/limits.py
openstackclient/common/module.py
openstackclient/common/pagination.py
openstackclient/common/progressbar.py
openstackclient/common/project_cleanup.py
openstackclient/common/quota.py
openstackclient/common/versions.py
openstackclient/compute/__init__.py
openstackclient/compute/client.py
openstackclient/compute/v2/__init__.py
openstackclient/compute/v2/agent.py
openstackclient/compute/v2/aggregate.py
openstackclient/compute/v2/console.py
openstackclient/compute/v2/console_connection.py
openstackclient/compute/v2/flavor.py
openstackclient/compute/v2/host.py
openstackclient/compute/v2/hypervisor.py
openstackclient/compute/v2/hypervisor_stats.py
openstackclient/compute/v2/keypair.py
openstackclient/compute/v2/server.py
openstackclient/compute/v2/server_backup.py
openstackclient/compute/v2/server_event.py
openstackclient/compute/v2/server_group.py
openstackclient/compute/v2/server_image.py
openstackclient/compute/v2/server_migration.py
openstackclient/compute/v2/server_volume.py
openstackclient/compute/v2/service.py
openstackclient/compute/v2/usage.py
openstackclient/identity/__init__.py
openstackclient/identity/client.py
openstackclient/identity/common.py
openstackclient/identity/v2_0/__init__.py
openstackclient/identity/v2_0/catalog.py
openstackclient/identity/v2_0/ec2creds.py
openstackclient/identity/v2_0/endpoint.py
python_openstackclient-8.3.0.dist-info/licenses/AUTHORS
python_openstackclient-8.3.0.dist-info/licenses/LICENSE
python_openstackclient-8.3.0.dist-info/METADATA
python_openstackclient-8.3.0.dist-info/WHEEL
python_openstackclient-8.3.0.dist-info/entry_points.txt
python_openstackclient-8.3.0.dist-info/pbr.json
python_openstackclient-8.3.0.dist-info/top_level.txt
python_openstackclient-8.3.0.dist-info/RECORD
